{
  "method": "rolling Pearson 20yr window, detrended",
  "results": {
    "1900-1920": {
      "r": -0.0083,
      "p": 0.9724
    },
    "1905-1925": {
      "r": 0.2114,
      "p": 0.3709
    },
    "1910-1930": {
      "r": 0.4503,
      "p": 0.0463
    },
    "1915-1935": {
      "r": 0.4749,
      "p": 0.0344
    },
    "1920-1940": {
      "r": 0.2119,
      "p": 0.3697
    },
    "1925-1945": {
      "r": 0.2854,
      "p": 0.2226
    },
    "1930-1950": {
      "r": 0.0675,
      "p": 0.7772
    },
    "1935-1955": {
      "r": -0.1124,
      "p": 0.6372
    },
    "1940-1960": {
      "r": -0.0857,
      "p": 0.7194
    },
    "1945-1965": {
      "r": -0.2542,
      "p": 0.2796
    },
    "1950-1970": {
      "r": -0.0946,
      "p": 0.6917
    },
    "1955-1975": {
      "r": -0.0385,
      "p": 0.872
    },
    "1960-1980": {
      "r": 0.3531,
      "p": 0.1267
    },
    "1965-1985": {
      "r": 0.4003,
      "p": 0.0803
    },
    "1970-1990": {
      "r": 0.5819,
      "p": 0.0071
    },
    "1975-1995": {
      "r": 0.5782,
      "p": 0.0076
    },
    "1980-2000": {
      "r": 0.5807,
      "p": 0.0073
    },
    "1985-2005": {
      "r": 0.4357,
      "p": 0.0548
    },
    "1990-2010": {
      "r": 0.1059,
      "p": 0.6567
    },
    "1995-2015": {
      "r": 0.1964,
      "p": 0.4066
    },
    "2000-2020": {
      "r": 0.3563,
      "p": 0.1231
    },
    "2005-2025": {
      "r": 0.5103,
      "p": 0.0215
    }
  },
  "significant_windows": [
    "1910-1930",
    "1915-1935",
    "1970-1990",
    "1975-1995",
    "1980-2000",
    "2005-2025"
  ],
  "n_significant": 6
}